CalculusForBeginnersMit/README.md
CalculusForBeginnersMit/__init__.py
CalculusForBeginnersMit/__main__.py
CalculusForBeginnersMit/file.epub
CalculusForBeginnersMit/index.html
CalculusForBeginnersMit/css/__init__.py
CalculusForBeginnersMit/css/annotations.css
CalculusForBeginnersMit/css/main.css
CalculusForBeginnersMit/css/normalize.css
CalculusForBeginnersMit/css/popup.css
CalculusForBeginnersMit/font/__init__.py
CalculusForBeginnersMit/font/fontello.eot
CalculusForBeginnersMit/font/fontello.svg
CalculusForBeginnersMit/font/fontello.ttf
CalculusForBeginnersMit/font/fontello.woff
CalculusForBeginnersMit/img/__init__.py
CalculusForBeginnersMit/img/annotator-glyph-sprite.png
CalculusForBeginnersMit/img/annotator-icon-sprite.png
CalculusForBeginnersMit/img/apple-touch-icon.png
CalculusForBeginnersMit/img/cancelfullscreen.png
CalculusForBeginnersMit/img/close.png
CalculusForBeginnersMit/img/fullscreen.png
CalculusForBeginnersMit/img/loader.gif
CalculusForBeginnersMit/img/menu-icon.png
CalculusForBeginnersMit/img/save.png
CalculusForBeginnersMit/img/saved.png
CalculusForBeginnersMit/img/settings-s.png
CalculusForBeginnersMit/img/settings.png
CalculusForBeginnersMit/img/star.png
CalculusForBeginnersMit/js/__init__.py
CalculusForBeginnersMit/js/epub.js
CalculusForBeginnersMit/js/epub.min.js
CalculusForBeginnersMit/js/epub.min.map
CalculusForBeginnersMit/js/hooks.min.js
CalculusForBeginnersMit/js/hooks.min.map
CalculusForBeginnersMit/js/reader.js
CalculusForBeginnersMit/js/reader.js.map
CalculusForBeginnersMit/js/reader.min.js
CalculusForBeginnersMit/js/reader.min.map
CalculusForBeginnersMit/js/hooks/__init__.py
CalculusForBeginnersMit/js/hooks/extensions/__init__.py
CalculusForBeginnersMit/js/hooks/extensions/highlight.js
CalculusForBeginnersMit/js/libs/__init__.py
CalculusForBeginnersMit/js/libs/jquery.min.js
CalculusForBeginnersMit/js/libs/localforage.min.js
CalculusForBeginnersMit/js/libs/screenfull.js
CalculusForBeginnersMit/js/libs/screenfull.min.js
calculus_for_beginners_mit-2024.3.2.0.dist-info/METADATA
calculus_for_beginners_mit-2024.3.2.0.dist-info/WHEEL
calculus_for_beginners_mit-2024.3.2.0.dist-info/entry_points.txt
calculus_for_beginners_mit-2024.3.2.0.dist-info/top_level.txt
calculus_for_beginners_mit-2024.3.2.0.dist-info/RECORD
